{"guide_components_breadcrumb.md":"C2K96r3q","guide_components_backtop.md":"CFfAqEa0","guide_components_alert.md":"Cp3jox91","guide_components_button.md":"cN2GTwEw","guide_components_carousel.md":"D61Vo1L3","guide_components_card.md":"Bhej_F7f","guide_components_badge.md":"BBJ1irNo","guide_components_avatar.md":"CMhZbqxf","guide_components_countdown.md":"BanSKSmB","guide_components_collapse.md":"BqqtojgZ","guide_components_checkbox.md":"CrXZUZBC","guide_components_cascader.md":"DCpqeG75","guide_components_divider.md":"CzGfVsWe","guide_components_empty.md":"5RSdJzJM","guide_components_ellipsis.md":"BmLe32Vr","guide_components_descriptions.md":"Dy1Ak61q","guide_components_drawer.md":"ClUER06K","guide_components_dialog.md":"yP7csq0O","guide_components_flex.md":"BGF-9kuh","guide_components_datepicker.md":"C-jJhIBa","guide_components_image.md":"BRyNhn7X","guide_components_inputnumber.md":"BnefzTw8","guide_components_modal.md":"BuHXmm6M","guide_components_message.md":"Q7MF0gjH","guide_components_notification.md":"DooqJMAx","guide_components_progress.md":"0r3k5ecq","guide_components_numberanimation.md":"CDMtS1LF","guide_components_input.md":"C2mAldGs","guide_components_pagination.md":"B919ZvlH","guide_components_qrcode.md":"CSerhV-o","guide_components_popconfirm.md":"D6NQi77T","guide_components_grid.md":"BM1KTWyy","guide_components_radio.md":"CYnTUGjk","guide_components_slider.md":"5dRRS6tX","guide_components_rate.md":"vHvwfp82","guide_components_result.md":"ClGNOg4R","guide_components_select.md":"BI6oUeHf","guide_components_space.md":"LW7W_KAM","guide_components_steps.md":"CQeoUlih","guide_components_spin.md":"CEjsv3wD","guide_components_swiper.md":"CBLSmQ5O","guide_components_statistic.md":"C8LGTEdu","guide_components_table.md":"BVwpAhNG","guide_components_switch.md":"CqdtX6T5","guide_components_tabs.md":"BmJRfgqT","guide_components_textscroll.md":"C2FHNbNt","guide_components_textarea.md":"Brpnk-WU","guide_components_video.md":"DXi2T7Re","guide_components_tooltip.md":"rkQAr_hf","guide_components_waterfall.md":"enHhGe-M","guide_features.md":"BxyLYQwa","index.md":"CpJ_a9kb","guide_started.md":"0hzZEQUt","guide_components_timeline.md":"Utspm1H6","utils_animation-frame.md":"QbonUE2S","utils_add.md":"Dwofb_dF","guide_components_upload.md":"CGvkVlsd","guide_components_tag.md":"CYnHEWUQ","utils_raf-timeout.md":"AyIY7GGw","utils_debounce.md":"C0M08Mxf","utils_date-format.md":"C8m3mbFn","utils_started.md":"C40k2MGy","utils_download-file.md":"B4R6f-aV","utils_toggle-dark.md":"BvisDlB1","utils_throttle.md":"DbWaTf01","utils_format-number.md":"Cvw77Eic","guide_components_watermark.md":"C_v5knkK"}
